siteship/__init__.py
siteship/cli.py
siteship/siteship.py
siteship-0.1.2.dist-info/DESCRIPTION.rst
siteship-0.1.2.dist-info/METADATA
siteship-0.1.2.dist-info/RECORD
siteship-0.1.2.dist-info/WHEEL
siteship-0.1.2.dist-info/entry_points.txt
siteship-0.1.2.dist-info/metadata.json
siteship-0.1.2.dist-info/top_level.txt
