Metadata-Version: 2.0
Name: siteship
Version: 0.1.2
Summary: Static websites deployments made simple
Home-page: https://github.com/siteship/siteship-cli
Author: Madis Väin
Author-email: madisvain@gmail.com
License: MIT license
Keywords: siteship
Platform: UNKNOWN
Classifier: Development Status :: 2 - Pre-Alpha
Classifier: Intended Audience :: Developers
Classifier: License :: OSI Approved :: MIT License
Classifier: Natural Language :: English
Classifier: Programming Language :: Python :: 2
Classifier: Programming Language :: Python :: 2.7
Classifier: Programming Language :: Python :: 3
Classifier: Programming Language :: Python :: 3.4
Classifier: Programming Language :: Python :: 3.5
Classifier: Programming Language :: Python :: 3.6
Requires-Dist: click (<7,>=6.0)
Requires-Dist: tinynetrc (==1.2.0)
Requires-Dist: requests (<3,>=2.18.4)
